{
    "number_of_answers_old": 47,
    "number_of_answers_new": 13,
    "all_concepts": [
        "remain",
        "elapsed",
        "time",
        "game",
        "counter",
        "current"
    ],
    "joint_concepts": [
        "game",
        "elapsed",
        "time"
    ],
    "concepts_only_old": [
        "remain",
        "counter",
        "current"
    ],
    "concepts_only_new": [],
    "concepts_counters_old": {
        "game": 23,
        "time": 47,
        "remain": 2,
        "elapsed": 8,
        "counter": 3,
        "current": 2
    },
    "concepts_counters_new": {
        "game": 10,
        "time": 13,
        "elapsed": 1
    },
    "concepts_distribution_old": {
        "game": {
            "game": 22,
            "play": 1
        },
        "time": {
            "time": 35,
            "timer": 6,
            "duration": 3,
            "t": 1,
            "clock": 2
        },
        "remain": {
            "left": 2
        },
        "elapsed": {
            "passed": 1,
            "elapsed": 4,
            "session": 1,
            "from_beginning": 1,
            "since_start": 1
        },
        "counter": {
            "counter": 3
        },
        "current": {
            "current": 2
        }
    },
    "concepts_distribution_new": {
        "game": {
            "game": 10
        },
        "time": {
            "time": 12,
            "duration": 1
        },
        "elapsed": {
            "passed": 1
        }
    },
    "concpets_mean_old": 1.8085106382978724,
    "concpets_mean_new": 1.8461538461538463,
    "concpets_var_old": 0.3250339520144862,
    "concpets_var_new": 0.13017751479289938,
    "variables_lengths_mean_old": 9.680851063829786,
    "variables_lengths_mean_new": 8.692307692307692,
    "variables_lengths_var_old": 22.983250339520147,
    "variables_lengths_var_new": 5.289940828402367
}